CHANGES.txt
LICENSE.txt
MANIFEST.in
README.txt
setup.py
CmtConvert.egg-info/PKG-INFO
CmtConvert.egg-info/SOURCES.txt
CmtConvert.egg-info/dependency_links.txt
CmtConvert.egg-info/entry_points.txt
CmtConvert.egg-info/top_level.txt
cmt_convert/__init__.py
cmt_convert/_utils.py
cmt_convert/convert.py
cmt_convert/decorator.py
cmt_convert/map.py
cmt_convert/plugin.py
cmt_convert/readers.py
cmt_convert/writers.py
cmt_convert/plugins/__init__.py
cmt_convert/plugins/asc.py
cmt_convert/plugins/ww3.py
cmt_convert/tests/__init__.py
cmt_convert/tests/test_utils.py
docs/faq.txt