Metadata-Version: 1.0
Name: CmtConvert
Version: 0.1.0
Summary: Plugin-based file format converter
Home-page: https://csdms.colorado.edu/trac/csdms
Author: Eric Hutton
Author-email: eric.hutton@colorado.edu
License: UNKNOWN
Platform: UNKNOWN
